espn_api/__init__.py
espn_api/_version.py
espn_api/base_league.py
espn_api/base_pick.py
espn_api/base_settings.py
espn_api/baseball/__init__.py
espn_api/baseball/activity.py
espn_api/baseball/box_player.py
espn_api/baseball/box_score.py
espn_api/baseball/constant.py
espn_api/baseball/league.py
espn_api/baseball/matchup.py
espn_api/baseball/player.py
espn_api/baseball/team.py
espn_api/baseball/utils.py
espn_api/basketball/__init__.py
espn_api/basketball/activity.py
espn_api/basketball/box_player.py
espn_api/basketball/box_score.py
espn_api/basketball/constant.py
espn_api/basketball/league.py
espn_api/basketball/matchup.py
espn_api/basketball/player.py
espn_api/basketball/team.py
espn_api/basketball/transaction.py
espn_api/football/__init__.py
espn_api/football/activity.py
espn_api/football/box_player.py
espn_api/football/box_score.py
espn_api/football/constant.py
espn_api/football/helper.py
espn_api/football/league.py
espn_api/football/matchup.py
espn_api/football/player.py
espn_api/football/settings.py
espn_api/football/team.py
espn_api/football/utils.py
espn_api/hockey/__init__.py
espn_api/hockey/activity.py
espn_api/hockey/box_player.py
espn_api/hockey/box_score.py
espn_api/hockey/constant.py
espn_api/hockey/league.py
espn_api/hockey/matchup.py
espn_api/hockey/player.py
espn_api/hockey/record.py
espn_api/hockey/team.py
espn_api/requests/__init__.py
espn_api/requests/constant.py
espn_api/requests/espn_requests.py
espn_api/utils/__init__.py
espn_api/utils/logger.py
espn_api/utils/utils.py
espn_api/wbasketball/__init__.py
espn_api/wbasketball/activity.py
espn_api/wbasketball/box_player.py
espn_api/wbasketball/box_score.py
espn_api/wbasketball/constant.py
espn_api/wbasketball/league.py
espn_api/wbasketball/matchup.py
espn_api/wbasketball/player.py
espn_api/wbasketball/team.py
espn_api-0.44.0.dist-info/LICENSE
espn_api-0.44.0.dist-info/METADATA
espn_api-0.44.0.dist-info/WHEEL
espn_api-0.44.0.dist-info/top_level.txt
espn_api-0.44.0.dist-info/RECORD
