Metadata-Version: 2.1
Name: espn-api
Version: 0.44.0
Summary: ESPN API
Home-page: https://github.com/cwendt94/espn-api
Author: Christian Wendt
License: UNKNOWN
Platform: UNKNOWN
Classifier: Programming Language :: Python :: 3
Classifier: License :: OSI Approved :: MIT License
Classifier: Operating System :: OS Independent
Requires-Dist: requests<3.0.0,>=2.0.0
Requires-Dist: urllib3<=2.2.3
